queutils/__init__.py
queutils/asyncqueue.py
queutils/awrap.py
queutils/countable.py
queutils/eventcounterqueue.py
queutils/filequeue.py
queutils/iterablequeue.py
queutils/py.typed
queutils-0.11.0.dist-info/METADATA
queutils-0.11.0.dist-info/WHEEL
queutils-0.11.0.dist-info/licenses/LICENSE
queutils-0.11.0.dist-info/RECORD
