Metadata-Version: 2.4
Name: queutils
Version: 0.11.0
Summary: Handy Python Queue utilies
Project-URL: Homepage, https://github.com/Jylpah/queutils
Project-URL: Bug Tracker, https://github.com/Jylpah/queutils/issues
Author-email: Jylpah <jylpah@gmail.com>
License-File: LICENSE
Classifier: Development Status :: 4 - Beta
Classifier: Framework :: AsyncIO
Classifier: License :: OSI Approved :: MIT License
Classifier: Operating System :: OS Independent
Classifier: Programming Language :: Python :: 3
Classifier: Topic :: Software Development :: Libraries
Requires-Python: >=3.11
Requires-Dist: aioconsole>=0.6
Requires-Dist: deprecated>=1.2.18
Provides-Extra: dev
Requires-Dist: build>=0.10; extra == 'dev'
Requires-Dist: hatchling>=1.22.4; extra == 'dev'
Requires-Dist: mypy>=1.8; extra == 'dev'
Requires-Dist: pip-chill>=1.0; extra == 'dev'
Requires-Dist: pytest-asyncio>=0.23; extra == 'dev'
Requires-Dist: pytest-cov>=4.1; extra == 'dev'
Requires-Dist: pytest-datafiles>=3.0; extra == 'dev'
Requires-Dist: pytest-timeout>=2.2; extra == 'dev'
Requires-Dist: pytest>=8.0; extra == 'dev'
Requires-Dist: ruff>=0.1.9; extra == 'dev'
Requires-Dist: types-deprecated>=1.2.15; extra == 'dev'
